README.rst
setup.py
hcconfig/__init__.py
hcconfig/interface.py
hcconfig.egg-info/PKG-INFO
hcconfig.egg-info/SOURCES.txt
hcconfig.egg-info/dependency_links.txt
hcconfig.egg-info/entry_points.txt
hcconfig.egg-info/requires.txt
hcconfig.egg-info/top_level.txt