Metadata-Version: 1.1
Name: hcconfig
Version: 0.1.1
Summary: Configure HC-05, HC-06 and other Bluetooth modules easily
Home-page: https://github.com/Bulebots/hcconfig
Author: Miguel Sánchez de León Peque
Author-email: peque@neosit.es
License: BSD License
Keywords: hcconfig bluetooth configuration hc-05 hc-06 hc-0x
Platform: UNKNOWN
Classifier: Development Status :: 3 - Alpha
Classifier: Topic :: Utilities
Classifier: License :: OSI Approved :: BSD License
Classifier: Programming Language :: Python :: 3
Classifier: Programming Language :: Python :: 3.5
Classifier: Programming Language :: Python :: 3.6
Classifier: Programming Language :: Python :: 3.7
Classifier: Programming Language :: Python :: Implementation :: CPython
